pixel_level_contrastive_learning/__init__.py
pixel_level_contrastive_learning/pixel_level_contrastive_learning.py
pixel_level_contrastive_learning-0.1.1.dist-info/LICENSE
pixel_level_contrastive_learning-0.1.1.dist-info/METADATA
pixel_level_contrastive_learning-0.1.1.dist-info/WHEEL
pixel_level_contrastive_learning-0.1.1.dist-info/top_level.txt
pixel_level_contrastive_learning-0.1.1.dist-info/RECORD
