Metadata-Version: 2.1
Name: pixel-level-contrastive-learning
Version: 0.1.1
Summary: Pixel-Level Contrastive Learning
Home-page: https://github.com/lucidrains/pixel-level-contrastive-learning
Author: Phil Wang
Author-email: lucidrains@gmail.com
License: MIT
Keywords: self-supervised learning,artificial intelligence
Platform: UNKNOWN
Classifier: Development Status :: 4 - Beta
Classifier: Intended Audience :: Developers
Classifier: Topic :: Scientific/Engineering :: Artificial Intelligence
Classifier: License :: OSI Approved :: MIT License
Classifier: Programming Language :: Python :: 3.6
Requires-Dist: einops
Requires-Dist: torch (>=1.6)
Requires-Dist: kornia (>=0.4.0)
